Workbook

Sheet README
A1: QuantumRegTech – FILE DỮ LIỆU CHO UI (nguồn dữ liệu duy nhất của app)
A3: • App KHÔNG đọc file này lúc chạy. Script `npm run data` (tự chạy trước dev / build / test) chuyển file này → src/data/*.json.
A4: • Không đổi tên sheet và tên cột ở dòng 1 (script đọc theo tên). Rê chuột vào ô tiêu đề để xem giải thích cột.
A5: • Ô NỀN VÀNG ghi 'TODO' = chưa có số liệu → UI hiển thị '—'. KHÔNG điền số ước lượng.
A6: • Ô NỀN XÁM = công thức (tự tính). Sửa số đầu vào ở Financials / Market / Params, không sửa ô công thức.
A7: • Sau khi sửa: lưu file bằng Excel / LibreOffice (để lưu kết quả công thức), rồi chạy `npm run data` và `npm test`.
A9: NGUỒN SỐ LIỆU
A10: • Số liệu chuẩn: Phụ lục B – Hồ sơ Vòng 1 (trước đây ghi trong docs/MOCK_DATA.md): Ri, β, Z, vùng, RFin, POSINT, ESGi, tỷ trọng, lợi nhuận.
A11: • Bổ sung từ AQ_Input.xlsx (file nhập liệu v3 của nhóm tài chính – đã dùng xong, không còn trong repo; bản gốc do nhóm tài chính giữ): Financials 2024 → X1–X5, giá 2025 (Market), sàn MCM, tên/phân ngành, TH cho Cổng 2, chỉ tiêu ESG thô.
A12: • Z tính lại từ BCTC 2024 khớp Phụ lục B (VNM 6,18 · SAB 6,51 · MCM 6,90 · SBT 1,80); lợi nhuận thực tế tính từ giá 2025 khớp Phụ lục B.
A14: CÁC SHEET
A15: Params – tham số chung · Companies – thông tin DN · Financials – BCTC 2024 (tỷ đồng) · ZScore – X1–X5, Z, vùng (công thức) · Market – β, giá, Ri, lợi nhuận thực tế
... A17: QUBO_Matrix – ma trận Q (để trống) · Private_Sample – kết quả mẫu Cổng 2 · ESG_ChiTieu – chỉ tiêu ESG thô 2024 (tham khảo, app chưa đọc) · Cho_xac_nhan – việc cần nhóm quyết định

Sheet Params
A1: key | B1: value | C1: note | D1: source
A2: rf | B2: 0.0277 | C2: Lãi suất phi rủi ro | D2: TPCP 10 năm – VIS Rating
A3: erp | B3: 0.0835 | C3: Phần bù rủi ro vốn cổ phần | D3: Damodaran – NYU Stern 2025
A4: capm_formula | B4: Ri = Rf + βi × ERP | C4: Công thức hiển thị trong báo cáo
A5: altman_formula | B5: Z = 1,2X1 + 1,4X2 + 3,3X3 + 0,6X4 + 1,0X5 | C5: Altman Z gốc – DN niêm yết
A6: z_safe | B6: 2.99 | C6: Z > ngưỡng này → Safe
A7: z_distress | B7: 1.81 | C7: Z < ngưỡng này → Distress; ở giữa → Grey
A8: zp_safe | B8: 2.9 | C8: Z' (DN chưa niêm yết, Altman 1983) – cần nhóm xác nhận
A9: zp_distress | B9: 1.23 | C9: Z' (DN chưa niêm yết, Altman 1983) – cần nhóm xác nhận
A10: posint_l1 | B10: 0.05 | C10: Điểm phạt OSINT mức 1
A11: posint_l2 | B11: 0.1 | C11: Điểm phạt OSINT mức 2
A12: posint_l3 | B12: 0.2 | C12: Điểm phạt OSINT mức 3 (tối thiểu)
A13: min_weight | B13: 0.15 | C13: Ràng buộc tỷ trọng tối thiểu
A14: max_weight | B14: 0.55 | C14: Ràng buộc tỷ trọng tối đa
A15: capital_vnd | B15: 100000000000 | C15: Vốn mô phỏng (VNĐ)
A16: solver | B16: classical-cobyla | C16: classical-cobyla | qaoa
A17: alpha | B17: TODO | C17: Trọng số lợi nhuận – lấy từ code Python
A18: beta | B18: TODO | C18: Trọng số rủi ro biến động – lấy từ code Python
A19: gamma | B19: TODO | C19: Trọng số ESG – lấy từ code Python
A20: delta | B20: TODO | C20: Trọng số phạt rủi ro – lấy từ code Python
A21: qubo_bits_per_asset | B21: 4 | C21: Số bit rời rạc / tài sản
A22: qubo_num_qubits | B22: 16 | C22: Số qubit
A23: data_source | B23: Phụ lục B – Hồ sơ Vòng 1; bổ sung AQ_Input.xlsx (BCTC 2024, giá 2025) | C23: Hiển thị ở báo cáo

Sheet Companies
A1: ticker | B1: name | C1: exchange | D1: subsector | E1: listed | F1: fy_end_month | G1: note
A2: VNM | B2: CTCP Sữa Việt Nam | C2: HOSE | D2: Sữa | E2: 1 | F2: 12
A3: SAB | B3: Tổng CTCP Bia - Rượu - Nước giải khát Sài Gòn | C3: HOSE | D3: Bia/NGK | E3: 1 | F3: 12
A4: MCM | B4: CTCP Giống bò sữa Mộc Châu | C4: HOSE | D4: Sữa | E4: 1 | F4: 12 | G4: Sàn: theo AQ_Input
A5: SBT | B5: CTCP Thành Thành Công – Biên Hòa (TTC AgriS) | C5: HOSE | D5: Đường | E5: 1 | F5: 6 | G5: Niên độ 1/7–30/6

Sheet Financials
A1: ticker | B1: fiscal_year | C1: period_note | D1: CA | E1: TA | F1: CL | G1: TL | H1: RE | I1: Revenue | J1: PBT | K1: Interest | L1: MktCap | M1: source
A2: VNM | B2: 2024 | C2: Năm 2024 | D2: 37553.65 | E2: 55049.06 | F2: 18459.55 | G2: 18874.66 | H2: 3471.22 | I2: 61823.89 | J2: 11599.65 | K2: 279.42 | L2: 120799.42 | M2: AQ_Input.xlsx – Financials (BCTC hợp nhất 2024)
A3: SAB | B3: 2024 | C3: Năm 2024 | D3: 25066.73 | E3: 33439.41 | F3: 8657.14 | G3: 9002.31 | H3: 9217.8 | I3: 32164.26 | J3: 5647.36 | K3: 27.45 | L3: 60280.43 | M3: AQ_Input.xlsx – Financials (BCTC hợp nhất 2024)
A4: MCM | B4: 2024 | C4: Năm 2024 | D4: 2114.93 | E4: 2686.67 | F4: 377.61 | G4: 381.49 | H4: 239.13 | I4: 2919.37 | J4: 252.06 | K4: 1.73 | L4: 2926 | M4: AQ_Input.xlsx – Financials (BCTC hợp nhất 2024)
A5: SBT | B5: 2024 | C5: Niên độ 2023–2024 (kết thúc 30/6/2024) – kiểm tra lại | D5: 23751.78 | E5: 34078.29 | F5: 19399.73 | G5: 22934.26 | H5: 1133.02 | I5: 29062.17 | J5: 907.86 | K5: 1724.69 | L5: 18808.11 | M5: AQ_Input.xlsx – Financials (BCTC hợp nhất 2024)

Sheet ZScore
A1: ticker | B1: model | C1: fiscal_year | D1: x1 | E1: x2 | F1: x3 | G1: x4 | H1: x5 | I1: z | J1: z_appendix | K1: zone | L1: rfin_base
A2: VNM | B2: Z | C2: 2024 | D2: =(INDEX(Financials!$D:$D,MATCH($A2,Financials!$A:$A,0))-INDEX(Financials!$F:$F,MATCH($A2,Financials!$A:$A,0)))/INDEX(Financials!$E:$E,MATCH($A2,Financials!$A:$A,0)) -> 0.34685606 | E2: =INDEX(Financials!$H:$H,MATCH($A2,Financials!$A:$A,0))/INDEX(Financials!$E:$E,MATCH($A2,Financials!$A:$A,0)) -> 0.063056844 | F2: =(INDEX(Financials!$J:$J,MATCH($A2,Financials!$A:$A,0))+INDEX(Financials!$K:$K,MATCH($A2,Financials!$A:$A,0)))/INDEX(Financials!$E:$E,MATCH($A2,Financials!$A:$A,0)) -> 0.21579061 | G2: =INDEX(Financials!$L:$L,MATCH($A2,Financials!$A:$A,0))/INDEX(Financials!$G:$G,MATCH($A2,Financials!$A:$A,0)) -> 6.4000846 | H2: =INDEX(Financials!$I:$I,MATCH($A2,Financials!$A:$A,0))/INDEX(Financials!$E:$E,MATCH($A2,Financials!$A:$A,0)) -> 1.1230689 | I2: =1.2*D2+1.4*E2+3.3*F2+0.6*G2+1*H2 -> 6.1797355 | J2: 6.18 | K2: =IF(I2>INDEX(Params!$B:$B,MATCH("z_safe",Params!$A:$A,0)),"safe",IF(I2>=INDEX(Params!$B:$B,MATCH("z_distress",Params!$A:$A,0)),"grey","distress")) -> safe | L2: 0.1
A3: SAB | B3: Z | C3: 2024 | D3: =(INDEX(Financials!$D:$D,MATCH($A3,Financials!$A:$A,0))-INDEX(Financials!$F:$F,MATCH($A3,Financials!$A:$A,0)))/INDEX(Financials!$E:$E,MATCH($A3,Financials!$A:$A,0)) -> 0.49072606 | E3: =INDEX(Financials!$H:$H,MATCH($A3,Financials!$A:$A,0))/INDEX(Financials!$E:$E,MATCH($A3,Financials!$A:$A,0)) -> 0.27565678 | F3: =(INDEX(Financials!$J:$J,MATCH($A3,Financials!$A:$A,0))+INDEX(Financials!$K:$K,MATCH($A3,Financials!$A:$A,0)))/INDEX(Financials!$E:$E,MATCH($A3,Financials!$A:$A,0)) -> 0.16970425 | G3: =INDEX(Financials!$L:$L,MATCH($A3,Financials!$A:$A,0))/INDEX(Financials!$G:$G,MATCH($A3,Financials!$A:$A,0)) -> 6.6961069 | H3: =INDEX(Financials!$I:$I,MATCH($A3,Financials!$A:$A,0))/INDEX(Financials!$E:$E,MATCH($A3,Financials!$A:$A,0)) -> 0.96186685 | I3: =1.2*D3+1.4*E3+3.3*F3+0.6*G3+1*H3 -> 6.5143458 | J3: 6.51 | K3: =IF(I3>INDEX(Params!$B:$B,MATCH("z_safe",Params!$A:$A,0)),"safe",IF(I3>=INDEX(Params!$B:$B,MATCH("z_distress",Params!$A:$A,0)),"grey","distress")) -> safe | L3: 0.1
A4: MCM | B4: Z | C4: 2024 | D4: =(INDEX(Financials!$D:$D,MATCH($A4,Financials!$A:$A,0))-INDEX(Financials!$F:$F,MATCH($A4,Financials!$A:$A,0)))/INDEX(Financials!$E:$E,MATCH($A4,Financials!$A:$A,0)) -> 0.64664436 | E4: =INDEX(Financials!$H:$H,MATCH($A4,Financials!$A:$A,0))/INDEX(Financials!$E:$E,MATCH($A4,Financials!$A:$A,0)) -> 0.089006093 | F4: =(INDEX(Financials!$J:$J,MATCH($A4,Financials!$A:$A,0))+INDEX(Financials!$K:$K,MATCH($A4,Financials!$A:$A,0)))/INDEX(Financials!$E:$E,MATCH($A4,Financials!$A:$A,0)) -> 0.094462662 | G4: =INDEX(Financials!$L:$L,MATCH($A4,Financials!$A:$A,0))/INDEX(Financials!$G:$G,MATCH($A4,Financials!$A:$A,0)) -> 7.6699258 | H4: =INDEX(Financials!$I:$I,MATCH($A4,Financials!$A:$A,0))/INDEX(Financials!$E:$E,MATCH($A4,Financials!$A:$A,0)) -> 1.0866128 | I4: =1.2*D4+1.4*E4+3.3*F4+0.6*G4+1*H4 -> 6.9008768 | J4: 6.9 | K4: =IF(I4>INDEX(Params!$B:$B,MATCH("z_safe",Params!$A:$A,0)),"safe",IF(I4>=INDEX(Params!$B:$B,MATCH("z_distress",Params!$A:$A,0)),"grey","distress")) -> safe | L4: 0.1
A5: SBT | B5: Z | C5: 2024 | D5: =(INDEX(Financials!$D:$D,MATCH($A5,Financials!$A:$A,0))-INDEX(Financials!$F:$F,MATCH($A5,Financials!$A:$A,0)))/INDEX(Financials!$E:$E,MATCH($A5,Financials!$A:$A,0)) -> 0.12770741 | E5: =INDEX(Financials!$H:$H,MATCH($A5,Financials!$A:$A,0))/INDEX(Financials!$E:$E,MATCH($A5,Financials!$A:$A,0)) -> 0.03324756 | F5: =(INDEX(Financials!$J:$J,MATCH($A5,Financials!$A:$A,0))+INDEX(Financials!$K:$K,MATCH($A5,Financials!$A:$A,0)))/INDEX(Financials!$E:$E,MATCH($A5,Financials!$A:$A,0)) -> 0.077250062 | G5: =INDEX(Financials!$L:$L,MATCH($A5,Financials!$A:$A,0))/INDEX(Financials!$G:$G,MATCH($A5,Financials!$A:$A,0)) -> 0.82008794 | H5: =INDEX(Financials!$I:$I,MATCH($A5,Financials!$A:$A,0))/INDEX(Financials!$E:$E,MATCH($A5,Financials!$A:$A,0)) -> 0.85280599 | I5: =1.2*D5+1.4*E5+3.3*F5+0.6*G5+1*H5 -> 1.7995794 | J5: 1.8 | K5: =IF(I5>INDEX(Params!$B:$B,MATCH("z_safe",Params!$A:$A,0)),"safe",IF(I5>=INDEX(Params!$B:$B,MATCH("z_distress",Params!$A:$A,0)),"grey","distress")) -> distress | L5: 0.7

Sheet Market
A1: ticker | B1: beta | C1: price_start_next | D1: price_end_next | E1: expected_return | F1: realized_return | G1: source
A2: VNM | B2: 0.59 | C2: 58.21 | D2: 61.2 | E2: =INDEX(Params!$B:$B,MATCH("rf",Params!$A:$A,0))+B2*INDEX(Params!$B:$B,MATCH("erp",Params!$A:$A,0)) -> 0.076965 | F2: =D2/C2-1 -> 0.051365745 | G2: β: Phụ lục B · giá: AQ_Input.xlsx – Market
A3: SAB | B3: 0.86 | C3: 50.16 | D3: 47 | E3: =INDEX(Params!$B:$B,MATCH("rf",Params!$A:$A,0))+B3*INDEX(Params!$B:$B,MATCH("erp",Params!$A:$A,0)) -> 0.09951 | F3: =D3/C3-1 -> -0.062998405 | G3: β: Phụ lục B · giá: AQ_Input.xlsx – Market
A4: MCM | B4: 0.72 | C4: 32.09 | D4: 26.35 | E4: =INDEX(Params!$B:$B,MATCH("rf",Params!$A:$A,0))+B4*INDEX(Params!$B:$B,MATCH("erp",Params!$A:$A,0)) -> 0.08782 | F4: =D4/C4-1 -> -0.17887192 | G4: β: Phụ lục B · giá: AQ_Input.xlsx – Market
A5: SBT | B5: 0.761 | C5: 11.68 | D5: 25.1 | E5: =INDEX(Params!$B:$B,MATCH("rf",Params!$A:$A,0))+B5*INDEX(Params!$B:$B,MATCH("erp",Params!$A:$A,0)) -> 0.0912435 | F5: =D5/C5-1 -> 1.1489726 | G5: β: Phụ lục B · giá: AQ_Input.xlsx – Market

Sheet ESG
A1: ticker | B1: esg_score | C1: E | D1: S | E1: G | F1: transparency | G1: compliance | H1: greenwashing_risk
A2: VNM | B2: 0.5759 | C2: TODO | D2: TODO | E2: TODO | F2: TODO | G2: TODO | H2: TODO
A3: SAB | B3: 0.5117 | C3: TODO | D3: TODO | E3: TODO | F3: TODO | G3: TODO | H3: TODO
A4: MCM | B4: 0.2519 | C4: TODO | D4: TODO | E4: TODO | F4: TODO | G4: TODO | H4: high
A5: SBT | B5: 0.5842 | C5: TODO | D5: TODO | E5: TODO | F5: TODO | G5: TODO | H5: TODO

Sheet ESG_Evidence
A1: ticker | B1: claim | C1: claim_source | D1: counter | E1: counter_source | F1: counter_url | G1: contradiction | H1: taxonomy_ref
A2: MCM | B2: TODO | C2: TODO | D2: Nguy cơ ô nhiễm môi trường từ hoạt động chăn nuôi bò sữa | E2: Tạp chí Môi trường và Xây dựng (2022) | F2: https://moitruongxaydungvn.vn/nguy-co-o-nhiem-moi-truong-tu-cong-ty-co-phan-giong-bo-sua-moc-chau | G2: 0.78 | H2: TODO

Sheet OSINT
A1: id | B1: ticker | C1: year | D1: month | E1: type | F1: severity | G1: penalty | H1: title | I1: source | J1: url | K1: active | L1: note
A2: evt-mcm-2022-01 | B2: MCM | C2: 2022 | D2: TODO | E2: environment | F2: 2 | G2: 0.1 | H2: Báo chí phản ánh nguy cơ ô nhiễm môi trường | I2: Tạp chí Môi trường và Xây dựng | J2: https://moitruongxaydungvn.vn/nguy-co-o-nhiem-moi-truong-tu-cong-ty-co-phan-giong-bo-sua-moc-chau | K2: 1 | L2: AQ_Input: 'Phản ánh môi trường (chưa có QĐ)'. Phụ lục B ghi 'Phạt xả thải' – xem Cho_xac_nhan

Sheet Portfolio
A1: ticker | B1: w_esg_aware | C1: w_baseline | D1: expected_return | E1: realized_return
A2: VNM | B2: 0.509 | C2: 0.15 | D2: =INDEX(Market!$E:$E,MATCH($A2,Market!$A:$A,0)) -> 0.076965 | E2: =INDEX(Market!$F:$F,MATCH($A2,Market!$A:$A,0)) -> 0.051365745
A3: SAB | B3: 0.191 | C3: 0.55 | D3: =INDEX(Market!$E:$E,MATCH($A3,Market!$A:$A,0)) -> 0.09951 | E3: =INDEX(Market!$F:$F,MATCH($A3,Market!$A:$A,0)) -> -0.062998405
A4: MCM | B4: 0.15 | C4: 0.15 | D4: =INDEX(Market!$E:$E,MATCH($A4,Market!$A:$A,0)) -> 0.08782 | E4: =INDEX(Market!$F:$F,MATCH($A4,Market!$A:$A,0)) -> -0.17887192
A5: SBT | B5: 0.15 | C5: 0.15 | D5: =INDEX(Market!$E:$E,MATCH($A5,Market!$A:$A,0)) -> 0.0912435 | E5: =INDEX(Market!$F:$F,MATCH($A5,Market!$A:$A,0)) -> 1.1489726

Sheet Portfolio_Summary
A1: scenario | B1: expected_return | C1: realized_return | D1: weight_sum | E1: appendix_expected | F1: appendix_realized
A2: esg_aware | B2: =SUMPRODUCT(Portfolio!B2:B5,Portfolio!D2:D5) -> 0.08504112 | C2: =SUMPRODUCT(Portfolio!B2:B5,Portfolio!E2:E5) -> 0.15962757 | D2: =SUM(Portfolio!B2:B5) -> 1 | E2: 0.085 | F2: 0.1596
A3: baseline | B3: =SUMPRODUCT(Portfolio!C2:C5,Portfolio!D2:D5) -> 0.093134775 | C3: =SUMPRODUCT(Portfolio!C2:C5,Portfolio!E2:E5) -> 0.11857084 | D3: =SUM(Portfolio!C2:C5) -> 1 | E3: 0.0931 | F3: 0.1186

Sheet Scenarios
A1: scenario_id | B1: alpha | C1: beta | D1: gamma | E1: delta | F1: VNM | G1: SAB | H1: MCM | I1: SBT | J1: note
A2: s1 | B2: 1 | C2: 1 | D2: 0 | E2: 0 | F2: 0.15 | G2: 0.55 | H2: 0.15 | I2: 0.15 | J2: = Baseline
A3: s2 | B3: 1 | C3: 1 | D3: 1 | E3: 1 | F3: 0.509 | G3: 0.191 | H3: 0.15 | I3: 0.15 | J3: = ESG-aware

Sheet QUBO_Matrix
A1: Dán ma trận Q 16×16 (số) vào vùng B3:Q18, hàng/cột q0…q15. Để trống = chưa có (UI hiện trạng thái rỗng).
B2: q0 | C2: q1 | D2: q2 | E2: q3 | F2: q4 | G2: q5 | H2: q6 | I2: q7 | J2: q8 | K2: q9 | L2: q10 | M2: q11 | N2: q12 | O2: q13 | P2: q14 | Q2: q15
A3: q0
A4: q1
A5: q2
A6: q3
A7: q4
A8: q5
A9: q6
A10: q7
A11: q8
A12: q9
A13: q10
A14: q11
... A18: q15

Sheet Private_Sample
A1: key | B1: value | C1: note
A2: company_name | B2: CTCP Chuỗi Sữa TH | C2: AQ_Input: TH chưa niêm yết – dùng cho nhóm so sánh ESG + Cổng 2
A3: subsector | B3: Sữa
A4: fiscal_year | B4: 2024
A5: z_model | B5: Z' | C5: Altman Z' cho DN chưa niêm yết
A6: x1 | B6: TODO | C6: AQ_Input chưa có BCTC của TH
A7: x2 | B7: TODO | C7: AQ_Input chưa có BCTC của TH
A8: x3 | B8: TODO | C8: AQ_Input chưa có BCTC của TH
A9: x4 | B9: TODO | C9: AQ_Input chưa có BCTC của TH
A10: x5 | B10: TODO | C10: AQ_Input chưa có BCTC của TH
A11: z | B11: TODO
A12: zone | B12: TODO | C12: safe | grey | distress
A13: rfin_base | B13: TODO
A14: esg_score | B14: TODO | C14: Có chỉ tiêu ESG thô của TH trong ESG_ChiTieu
A15: E | B15: TODO
A16: S | B16: TODO
A17: G | B17: TODO
A18: transparency | B18: TODO
A19: compliance | B19: TODO
A20: greenwashing_risk | B20: TODO
A21: posint | B21: TODO | C21: Sự kiện TH 2023 chưa xác minh pháp nhân – xem Cho_xac_nhan

Sheet ESG_ChiTieu
A1: code | B1: name | C1: type | D1: pol | E1: use | F1: VNM | G1: SAB | H1: MCM | I1: SBT | J1: TH
A2: E_01 | B2: Tổng phát thải khí nhà kính Scope 1 & 2 (tấn CO2e) | C2: Num | D2: (-) | E2: 0 | F2: 252175.37 | G2: 70888 | H2: 9548.93 | I2: 66687.7 | J2: 339425
A3: E_02 | B3: Cường độ phát thải (tấn CO2e/tỷ đồng doanh thu) | C3: Num | D3: (-) | E3: 1 | F3: 4.08 | G3: 2.224 | H3: 3.27 | I3: 2.34
A4: E_03 | B4: Chính sách/Cam kết giảm phát thải (Net Zero) | C4: Bool | D4: (+) | E4: 1 | F4: 1 | G4: 1 | H4: 0 | I4: 1 | J4: 1
A5: E_04 | B5: Chứng nhận Trung hòa Carbon (PAS 2060) | C5: Bool | D5: (+) | E5: 1 | F5: 1 | G5: 0 | H5: 0 | I5: 0 | J5: 0
A6: E_05 | B6: Hệ thống quản lý môi trường (ISO 14001) | C6: Bool | D6: (+) | E6: 1 | F6: 1 | G6: 1 | H6: 0 | I6: 1 | J6: 1
A7: E_06 | B7: Tổng lượng nước tiêu thụ (m3) – code tự chia doanh thu | C7: Num | D7: (-) | E7: 1 | F7: 4122231 | G7: 1311990 | I7: 5250693 | J7: 6394459
A8: E_07 | B8: Tỷ lệ nước tái sử dụng/tuần hoàn (%) | C8: Num | D8: (+) | E8: 1 | F8: 34.4 | G8: 5.7 | I8: 33.18 | J8: 37.1
A9: E_08 | B9: Tổng năng lượng tiêu thụ (GJ) – code tự chia doanh thu | C9: Num | D9: (-) | E9: 1 | F9: 2387796 | G9: 825554 | I9: 604680 | J9: 1020968
A10: E_09 | B10: Tỷ lệ năng lượng tái tạo (%) | C10: Num | D10: (+) | E10: 1 | F10: 33.03 | G10: 40.54 | I10: 91.04 | J10: 15.23
A11: E_10 | B11: Chính sách quản lý chất thải/bao bì nhựa | C11: Bool | D11: (+) | E11: 1 | F11: 1 | G11: 1 | H11: 1 | I11: 1 | J11: 1
A12: E_11 | B12: Chi đầu tư cho R&D/Công nghệ xanh (VND) | C12: Bool | D12: (+) | E12: 1 | F12: 1 | G12: 1 | H12: 1 | I12: 1 | J12: 1
A13: E_12 | B13: Sản phẩm đạt chuẩn Organic/Green | C13: Bool | D13: (+) | E13: 1 | F13: 1 | G13: 0 | H13: 0 | I13: 1 | J13: 1
A14: S_01 | B14: Tổng số nhân viên (Quy mô lao động) | C14: Num | D14: (+) | E14: 0 | F14: 9225 | G14: 4118 | H14: 772 | I14: 2651 | J14: 10000
A15: S_02 | B15: Tỷ lệ nữ giới trong ban quản lý cấp cao ( ban điều hành) (%) | C15: Num | D15: (+) | E15: 1 | F15: 26.5 | G15: 28.57 | H15: 0 | I15: 33.33 | J15: 31
A16: S_03 | B16: Số giờ đào tạo trung bình/nhân viên | C16: Num | D16: (+) | E16: 1 | F16: 50.3 | G16: 12.1 | I16: 44.06 | J16: 33.4
A17: S_04 | B17: Có công bố tỷ lệ thôi việc (Turnover rate) | C17: Bool | D17: (+) | E17: 1 | F17: 1 | G17: 1 | H17: 0 | I17: 1 | J17: 1
A18: S_05 | B18: Hoạt động, chính sách, chi phí đầu tư và sự tuân thủ cho sự an toàn của lao động | C18: Bool | D18: (+) | E18: 1 | F18: 1 | G18: 1 | H18: 1 | I18: 1 | J18: 1
A19: S_06 | B19: Công bố về tai nạn lao động | C19: Bool | D19: (+) | E19: 1 | F19: 1 | G19: 1 | H19: 0 | I19: 1 | J19: 1
A20: S_07 | B20: Chính sách an toàn sức khỏe nghề nghiệp (ISO 45001) | C20: Bool | D20: (+) | E20: 1 | F20: 1 | G20: 1 | H20: 0 | I20: 1 | J20: 0
A21: S_08 | B21: Có các chương trình Cộng đồng Chiến lược | C21: Bool | D21: (+) | E21: 1 | F21: 1 | G21: 1 | H21: 1 | I21: 1 | J21: 1
A22: S_09 | B22: Tổng ngân sách đóng góp xã hội (tỷ đồng) – code tự chia doanh thu | C22: Num | D22: (+) | E22: 1 | F22: 75 | G22: 42.11 | H22: 1.176 | I22: 11.65 | J22: 95.2
A23: S_10 | B23: Chính sách chống lao động trẻ em/cưỡng bức | C23: Bool | D23: (+) | E23: 1 | F23: 1 | G23: 1 | H23: 1 | I23: 1 | J23: 1
A24: S_11 | B24: Chính sách đa dạng và bình đẳng (D&I) | C24: Bool | D24: (+) | E24: 1 | F24: 1 | G24: 1 | H24: 1 | I24: 1 | J24: 1
A25: S_12 | B25: Chứng nhận ATTP (FSSC 22000/HACCP/ISO 22000) | C25: Bool | D25: (+) | E25: 1 | F25: 1 | G25: 1 | H25: 1 | I25: 1 | J25: 1
A26: S_13 | B26: Bảo mật thông tin khách hàng/An ninh mạng | C26: Bool | D26: (+) | E26: 1 | F26: 1 | G26: 1 | H26: 1 | I26: 1 | J26: 1
A27: G_01 | B27: Quy mô Hội đồng quản trị (HĐQT) | C27: Num | D27: (+) | E27: 1 | F27: 10 | G27: 7 | H27: 6 | I27: 8
A28: G_02 | B28: Tỷ lệ thành viên HĐQT độc lập (%) | C28: Num | D28: (+) | E28: 1 | F28: 30 | G28: 28.57 | H28: 16.66 | I28: 25
A29: G_03 | B29: Tách biệt vai trò Chủ tịch và Tổng giám đốc | C29: Bool | D29: (+) | E29: 1 | F29: 1 | G29: 1 | H29: 1 | I29: 1 | J29: 1
A30: G_04 | B30: Tỷ lệ nữ giới trong HĐQT | C30: Num | D30: (+) | E30: 1 | F30: 30 | G30: 28.57 | H30: 16.66 | I30: 37.5
A31: G_05 | B31: Có Tiểu ban/Ban phụ trách PTBV trực thuộc HĐQT hoặc Ban điều hành | C31: Bool | D31: (+) | E31: 1 | F31: 1 | G31: 1 | H31: 0 | I31: 1 | J31: 1
A32: G_06 | B32: Báo cáo PTBV được kiểm toán/đảm bảo độc lập | C32: Bool | D32: (+) | E32: 1 | F32: 1 | G32: 1 | H32: 0 | I32: 1 | J32: 1
A33: G_07 | B33: Doanh nghiệp có công bố Báo cáo tài chính theo chuẩn IFRS | C33: Bool | D33: (+) | E33: 1 | F33: 1 | G33: 0 | H33: 0 | I33: 1 | J33: 0

Sheet Cho_xac_nhan
A1: id | B1: topic | C1: issue | D1: decision | E1: status
A2: 1 | B2: Phiên bản mô hình | C2: AQ_Input v3 dùng Z''-EM (ngưỡng 2,6 / 1,1), sàn 5%, trần 40%, γ = 0,04, δ = 0,1 – khác Phụ lục B (Z gốc 2,99 / 1,81; 15–55%). | D2: GIỮ Phụ lục B. Mọi số công bố (tỷ trọng, lợi nhuận, +4,11 điểm %) được tính theo mô hình này và đã kiểm chứng lại từ BCTC/giá; ngưỡng 2,6 / 1,1 thuộc công thức Z''-EM nên không áp được cho Z gốc; v3 chưa đủ dữ liệu (MCH, năm 2023) và chưa có kết quả tối ưu. Chuyển sang v3 (nếu có ở Vòng 2) phải làm trọn gói: công thức, ngưỡng, ràng buộc, tỷ trọng, kết quả. | E2: Đã quyết
A3: 2 | B3: OSINT MCM 2022 | C3: Phụ lục B: 'Phạt xả thải môi trường'; AQ_Input: 'Phản ánh môi trường (chưa có QĐ)'. | D3: DÙNG mô tả AQ_Input ('Báo chí phản ánh nguy cơ ô nhiễm môi trường'), GIỮ penalty 0,10. AQ_Input là nguồn mới và cụ thể hơn, nói rõ chưa có quyết định xử phạt; ghi 'bị phạt' về một DN thật khi không có QĐ là sai sự thật. Rubric AQ_Input cũng chấm 'phản ánh chưa có QĐ' = 0,10 nên POSINT, RFin,Total và kết quả danh mục không đổi. Việc còn lại: bổ sung tháng + sửa lời thuyết minh/slide 'phạt xả thải'. | E3: Đã quyết
A4: 3 | B4: OSINT SAB 2024 | C4: Sự kiện 'Phạt VPHC thủ tục/sắc thuế' chưa có số QĐ + link. | D4: KHÔNG đưa vào dữ liệu. Chính quy tắc của AQ_Input: 'OSINT chỉ ghi sự kiện CÓ NGUỒN (link/số QĐ)'. Giữ POSINT SAB = 0 như Phụ lục B. Khi có nguồn: thêm dòng OSINT (mức 1, +0,05 → RFin,Total SAB = 0,15) và chạy lại tối ưu vì tỷ trọng sẽ đổi. | E4: Đã quyết
A5: 4 | B5: OSINT TH 2023 | C5: 'Trang trại bò sữa TH (Phú Yên) bị phạt 560 triệu đồng' – nguồn ghi 'xác minh pháp nhân'. | D5: KHÔNG đưa vào Private_Sample. Chưa xác minh được đúng pháp nhân bị phạt; cùng quy tắc 'chỉ ghi sự kiện có nguồn xác thực'. Khi xác minh xong thì thêm vào Private_Sample. | E5: Đã quyết
A6: 5 | B6: Điểm trụ cột ESG | C6: E, S, G, Minh bạch, Tuân thủ chưa có. | D6: ĐỂ TRỐNG (TODO). Tự chấm điểm = tự đặt phương pháp; điểm tự tính sẽ không khớp ESGi đã công bố (radar mâu thuẫn con số tổng); 'Minh bạch', 'Tuân thủ' không có nhóm chỉ tiêu riêng trong AQ_Input. Khi có aq_v3.py: chạy trên sheet ESG_ChiTieu (w_E 0,4 · w_S 0,35 · w_G 0,25) rồi điền vào sheet ESG. | E6: Đã quyết
A7: 6 | B7: β SBT | C7: Phụ lục B: 0,761; AQ_Input Market: 0,76. | D7: GIỮ 0,761. 0,76 là số làm tròn; 0,761 cho Ri = 9,12% khớp Phụ lục B. | E7: Đã quyết
A8: 7 | B8: SBT niên độ | C8: BCTC dùng niên độ kết thúc 30/6/2024 (AQ_Input ghi 'kiểm tra lại'). | D8: Nhóm tài chính xác nhận lại với BCTC kiểm toán. | E8: Mở
A9: 8 | B9: Tham số α β γ δ, QUBO, kịch bản | C9: Chưa có trong hồ sơ. | D9: IT lấy từ code Python: α β γ δ vào Params, ma trận Q 16×16 vào QUBO_Matrix, thêm 10–20 kịch bản vào Scenarios. | E9: Mở
